dj_pylibmc/__init__.py
dj_pylibmc/memcached.py
dj_pylibmc-0.6.4.dist-info/LICENSE
dj_pylibmc-0.6.4.dist-info/METADATA
dj_pylibmc-0.6.4.dist-info/WHEEL
dj_pylibmc-0.6.4.dist-info/top_level.txt
dj_pylibmc-0.6.4.dist-info/RECORD
