Metadata-Version: 2.1
Name: dj-pylibmc
Version: 0.6.4
Summary: Django cache backend using pylibmc
Home-page: https://github.com/RegioHelden/dj-pylibmc
Author: Jeff Balogh
Author-email: entwicklung@regiohelden.de
License: BSD
Keywords: django cache pylibmc memcached
Platform: UNKNOWN
Classifier: Development Status :: 4 - Beta
Classifier: Environment :: Web Environment
Classifier: Environment :: Web Environment :: Mozilla
Classifier: Framework :: Django
Classifier: Framework :: Django :: 2.2
Classifier: Framework :: Django :: 3.0
Classifier: Framework :: Django :: 3.1
Classifier: Intended Audience :: Developers
Classifier: License :: OSI Approved :: BSD License
Classifier: Operating System :: OS Independent
Classifier: Programming Language :: Python
Classifier: Programming Language :: Python :: 3.6
Classifier: Programming Language :: Python :: 3.7
Classifier: Programming Language :: Python :: 3.8
Classifier: Topic :: Software Development :: Libraries :: Python Modules
Requires-Dist: pylibmc (>=1.4.1)
